{
  "name": "!Bluray 1080p x265",
  "includeCustomFormatWhenRenaming": false,
  "specifications": [
    {
      "name": "1080p",
      "implementation": "ResolutionSpecification",
      "negate": false,
      "required": true,
      "fields": {
        "value": 1080
      }
    },
    {
      "name": "Bluray",
      "implementation": "SourceSpecification",
      "negate": false,
      "required": true,
      "fields": {
        "value": 9
      }
    },
    {
      "name": "x265/HEVC",
      "implementation": "ReleaseTitleSpecification",
      "negate": false,
      "required": true,
      "fields": {
        "value": "[xh][ ._-]?265|\\bHEVC(\\b|\\d)"
      }
    }
  ]
}
